{
	"FILE":[{
		"FILE_NAME":"A01_B02_C00_D02_0813_G01_F10_6_5.jpg",
		"COLLECTIONMETHOD":"블랙박스",
		"DAY/NIGHT":"주",
		"LANE":"다선",
		"ROADNUMBER":"제보영상",
		"PLACE":"제보영상",
		"IDCODE":"F10",
		"DATE":"2021.08.13",
		"WEATHER":"흐린날",
		"RESOLUTION":"1920*1080",
		"MAKE":"제보영상",
		"MODELNAME":"제보영상",
		"FILESIZE":"299335",
		"BOUNDINGCOUNT":"1",
		"ITEMS":[
			{
			"DRAWING":"Box",
			"SEGMENT":"대형차",
			"BOX":"1225.69,361.62,446.16,270.7",
			"POLYGON":"",
			"PACKAGE":"정상차량",
			"CLASS":"정상차량",
			"COVER":"",
			"COURSE":"후면좌측",
			"CURVE":"정상주행"
			}
		]
	}]
}